japanese_verb_conjugator_v2/__init__.py
japanese_verb_conjugator_v2/constants/__init__.py
japanese_verb_conjugator_v2/constants/enumerated_types.py
japanese_verb_conjugator_v2/constants/exceptions.py
japanese_verb_conjugator_v2/constants/irregular_verb_forms.py
japanese_verb_conjugator_v2/constants/irregular_verb_groups.py
japanese_verb_conjugator_v2/constants/particle_constants.py
japanese_verb_conjugator_v2/constants/verb_ending_constants.py
japanese_verb_conjugator_v2/copula_gen.py
japanese_verb_conjugator_v2/decorators.py
japanese_verb_conjugator_v2/negative_form_gen.py
japanese_verb_conjugator_v2/positive_form_gen.py
japanese_verb_conjugator_v2/utils.py
japanese_verb_conjugator_v2/verb_form_gen.py
japanese_verb_conjugator_v2-1.0.1.dist-info/LICENSE
japanese_verb_conjugator_v2-1.0.1.dist-info/METADATA
japanese_verb_conjugator_v2-1.0.1.dist-info/WHEEL
japanese_verb_conjugator_v2-1.0.1.dist-info/RECORD
