Metadata-Version: 2.3
Name: japanese-verb-conjugator-v2
Version: 1.0.1
Summary: Fork of the project https://github.com/jshiohaha/JapaneseVerbConjugator
License: BSD
Keywords: japanese,verb,conjugation,romaji,hiragana,katakana,kanji
Author: Jacob Shiohira
Maintainer: Markus Kruse
Maintainer-email: belshazzar314@gmail.com
Requires-Python: >=3.9,<4.0
Classifier: Development Status :: 5 - Production/Stable
Classifier: Intended Audience :: Developers
Classifier: License :: OSI Approved :: BSD License
Classifier: License :: Other/Proprietary License
Classifier: Operating System :: OS Independent
Classifier: Programming Language :: Python :: 3
Classifier: Programming Language :: Python :: 3.9
Classifier: Programming Language :: Python :: 3.10
Classifier: Programming Language :: Python :: 3.11
Classifier: Programming Language :: Python :: 3.12
Classifier: Programming Language :: Python :: 3.13
Classifier: Topic :: Text Processing :: Linguistic
Requires-Dist: python-romkan-ng (>=0.3.0,<0.4.0)
